this_is_vvvv/__init__.py
this_is_vvvv-0.1.dist-info/METADATA
this_is_vvvv-0.1.dist-info/WHEEL
this_is_vvvv-0.1.dist-info/top_level.txt
this_is_vvvv-0.1.dist-info/RECORD
